imagehide/__init__.py
imagehide-0.0.2.dist-info/METADATA
imagehide-0.0.2.dist-info/WHEEL
imagehide-0.0.2.dist-info/entry_points.txt
imagehide-0.0.2.dist-info/top_level.txt
imagehide-0.0.2.dist-info/RECORD
