Metadata-Version: 2.1
Name: imagehide
Version: 0.0.2
Summary: This was made and developed by techraj (@Teja Swaroop). I've just converted it to a wheel file :)
Home-page: UNKNOWN
Author: Aditya Khemka
License: MIT
Platform: UNKNOWN
Classifier: License :: OSI Approved :: MIT License
Classifier: Programming Language :: Python :: 3
Requires-Dist: requests
Requires-Dist: colorama
Requires-Dist: commonmark
Requires-Dist: Pillow
Requires-Dist: pycryptodome
Requires-Dist: pyfiglet
Requires-Dist: Pygments
Requires-Dist: rich
Requires-Dist: termcolor
Requires-Dist: typing-extensions
Requires-Dist: image
Requires-Dist: crypto
